Phi/__init__.py
Phi/finished_methods.py
Phi/phi.dll
IRonTeste-0.0.6.dist-info/LICENSE
IRonTeste-0.0.6.dist-info/METADATA
IRonTeste-0.0.6.dist-info/WHEEL
IRonTeste-0.0.6.dist-info/top_level.txt
IRonTeste-0.0.6.dist-info/RECORD
